config_server/__init__.py
config_server/app.py
config_server/attribute_dict.py
config_server/colors.py
config_server/config_server.py
config_server/core/__init__.py
config_server/core/request.py
core/__init__.py
core/request.py
daemondev_config_server-0.6.dist-info/LICENSE.txt
daemondev_config_server-0.6.dist-info/METADATA
daemondev_config_server-0.6.dist-info/WHEEL
daemondev_config_server-0.6.dist-info/top_level.txt
daemondev_config_server-0.6.dist-info/RECORD
