Metadata-Version: 2.1
Name: daemondev-config-server
Version: 0.6
Summary: Config-Files downloader
Home-page: https://github.com/daemondev/daemondev-config-server
Author: @daemondev
Author-email: granlinux@gmail.com
License: MIT
Classifier: Programming Language :: Python :: 3
Classifier: License :: OSI Approved :: MIT License
Classifier: Operating System :: OS Independent
Requires-Python: >=3.6
License-File: LICENSE.txt
Requires-Dist: pyyaml
